cryptonice/__init__.py
cryptonice/__main__.py
cryptonice/checkport.py
cryptonice/getdns.py
cryptonice/getentropy.py
cryptonice/getgeo.py
cryptonice/gethttp.py
cryptonice/gethttp2.py
cryptonice/gettls.py
cryptonice/jarm.py
cryptonice/output.py
cryptonice/pwnedkeys.py
cryptonice/scanner.py
cryptonice/technologies.json
cryptonice/wappalyze.py
cryptonice-1.4.2.3.dist-info/LICENSE
cryptonice-1.4.2.3.dist-info/METADATA
cryptonice-1.4.2.3.dist-info/WHEEL
cryptonice-1.4.2.3.dist-info/entry_points.txt
cryptonice-1.4.2.3.dist-info/top_level.txt
cryptonice-1.4.2.3.dist-info/RECORD
