Metadata-Version: 2.1
Name: cryptonice
Version: 1.4.2.3
Summary: Perform TLS scan of a domain
Home-page: https://github.com/F5-Labs/cryptonice
Author: F5 Labs
Author-email: f5labs@f5.com
License: MIT
Platform: UNKNOWN
Classifier: License :: OSI Approved :: MIT License
Classifier: Programming Language :: Python :: 3
Classifier: Programming Language :: Python :: 3.7
Requires-Python: >=3
Requires-Dist: beautifulsoup4 (>=4.9.0)
Requires-Dist: dnspython (>=2.0.0)
Requires-Dist: regex (>=2020.5.14)
Requires-Dist: sslyze (>=4.0.0)
Requires-Dist: urllib3 (>=1.22)
